kirlent/__init__.py
kirlent/env
kirlent/kirlent.json
kirlent/slides.py
kirlent/tasks.py
kirlent/templates.py
kirlent/utils.py
kirlent-0.5.1.dist-info/entry_points.txt
kirlent-0.5.1.dist-info/LICENSE.txt
kirlent-0.5.1.dist-info/WHEEL
kirlent-0.5.1.dist-info/METADATA
kirlent-0.5.1.dist-info/RECORD
